{"version": "1", "message": "ERROR: Hidden Testcases server unreachable.", "problem_id": "ads2_m3_a1_1", "user_id": "Someshwar95", "score": {"sample": {"0": {"execution_time": 0.20850300788879395, "passed": true}, "1": {"execution_time": 0.2853233814239502, "passed": true}, "2": {"execution_time": 0.23136472702026367, "passed": true}, "3": {"execution_time": 0.2486584186553955, "passed": true}, "4": {"execution_time": 0.3182234764099121, "passed": true}, "5": {"execution_time": 0.17099213600158691, "passed": true}, "6": {"execution_time": 0.29853248596191406, "passed": true}, "7": {"execution_time": 0.3015577793121338, "passed": true}}}, "check_style_score": "0/1"}